graphlite
tests
