Metadata-Version: 1.0
Name: graphlite
Version: 1.0.3
Summary: embedded graph datastore
Home-page: https://github.com/eugene-eeo/graphlite
Author: Eugene Eeo
Author-email: packwolf58@gmail.com
License: UNKNOWN
Platform: UNKNOWN
